{"Users":[{"UserUUID":"0","Projects":[{"Name":"Local","ProjectUUID":"","Servers":[{"ConnType":"MSSQL","Name":"SQLServer","SettingsSavePath":"/home/josue/.config/navicat/Settings/0/0/MSSQL/SQLServer","ServiceProvider":"Default","Hostname":"localhost","Port":1433,"InitialDatabase":"master","AuthType":"SQLServer","Domain":"","Username":"sa","Password":"7CC36AE49F23C0D550AEFB436DB4E3E6","SavePassword":true,"UseKeepAlive":false,"KeepAliveInterval":240,"UseEncryption":false,"IsAutoConnect":false,"SessionLimit":0,"UseCustomDBList":false,"CustomDBList":[],"UseSSH":false,"SSH":{"Host":"","Port":22,"UserName":"","AuthMethod":"Password","Password":"E191AF42327478CC5F143EF279EC4D81","SavePassword":true,"PrivateKeyPath":"","Passphrase":"E191AF42327478CC5F143EF279EC4D81","SavePassphrase":true,"UseCompression":false},"Profiles":[],"ActiveServerSettings":"","CreateTime":1680475197,"ModifyTime":1682437828,"NSYCreatedUser":"","NSYModifiedUser":"","NSYModifiedUserUUID":"","NSYCreatedUnixTimestamp":0,"NSYModifiedUnixTimestamp":0,"CommitUUID":"","ConnectionUUID":"","UnknownJsonPropertiesString":"","CloudSyncStatus":"Ready","ServerVersionStr":"15.00.4298","ServerVersion":15004298},{"ConnType":"PGSQL","Name":"PostgreSQL","SettingsSavePath":"/home/josue/.config/navicat/Settings/0/0/PGSQL/PostgreSQL","ServiceProvider":"Default","Hostname":"localhost","Port":5432,"InitialDatabase":"postgres","Username":"","Password":"E191AF42327478CC5F143EF279EC4D81","SavePassword":true,"UseKeepAlive":false,"KeepAliveInterval":240,"IsAutoConnect":false,"SessionLimit":0,"UseCustomDBList":false,"CustomDBList":[],"ClientDriverEncoding":"","ClientEncoding":65001,"UseSSL":false,"SSL":{"Mode":"Require","UseAuth":false,"ClientCertFile":"","ClientKeyFile":"","CACert":"","VerifyCA":false,"Cipher":"","RootCert":"","CRLFile":"","WeakCertValidation":true,"AllowInvalidHostName":false,"ClientKeyPassword":"","SaveClientKeyPassword":true},"UseSSH":false,"SSH":{"Host":"","Port":22,"UserName":"","AuthMethod":"Password","Password":"E191AF42327478CC5F143EF279EC4D81","SavePassword":true,"PrivateKeyPath":"","Passphrase":"E191AF42327478CC5F143EF279EC4D81","SavePassphrase":true,"UseCompression":false},"UseHTTP":false,"HTTPTunnel":{"URL":"","EncodeBase64":false,"UsePasswordAuth":false,"Username":"","Password":"E191AF42327478CC5F143EF279EC4D81","SavePassword":true,"UseCertAuth":false,"ClientKey":"","ClientCert":"","CACert":"","Passphrase":"E191AF42327478CC5F143EF279EC4D81","UseProxy":false,"Host":"","Port":8080,"ProxyUsername":"","ProxyPassword":"E191AF42327478CC5F143EF279EC4D81","SaveProxyPassword":true},"Profiles":[],"ActiveServerSettings":"","CreateTime":1684173311,"ModifyTime":1684173311,"NSYCreatedUser":"","NSYModifiedUser":"","NSYModifiedUserUUID":"","NSYCreatedUnixTimestamp":0,"NSYModifiedUnixTimestamp":0,"CommitUUID":"","ConnectionUUID":"","UnknownJsonPropertiesString":"","CloudSyncStatus":"Ready","ServerVersionStr":"150002","ServerVersion":150002},{"ConnType":"MSSQL","Name":"CloudClustersSQLServer","SettingsSavePath":"/home/josue/.config/navicat/Settings/0/0/MSSQL/CloudClustersSQLServer","ServiceProvider":"Default","Hostname":"mssql-126967-0.cloudclusters.net","Port":10149,"InitialDatabase":"master","AuthType":"SQLServer","Domain":"","Username":"josue","Password":"7CC36AE49F23C0D550AEFB436DB4E3E6","SavePassword":true,"UseKeepAlive":false,"KeepAliveInterval":240,"UseEncryption":true,"IsAutoConnect":false,"SessionLimit":0,"UseCustomDBList":false,"CustomDBList":[],"UseSSH":false,"SSH":{"Host":"","Port":22,"UserName":"","AuthMethod":"Password","Password":"E191AF42327478CC5F143EF279EC4D81","SavePassword":true,"PrivateKeyPath":"","Passphrase":"E191AF42327478CC5F143EF279EC4D81","SavePassphrase":true,"UseCompression":false},"Profiles":[],"ActiveServerSettings":"","CreateTime":1684177295,"ModifyTime":1684361778,"NSYCreatedUser":"","NSYModifiedUser":"","NSYModifiedUserUUID":"","NSYCreatedUnixTimestamp":0,"NSYModifiedUnixTimestamp":0,"CommitUUID":"","ConnectionUUID":"","UnknownJsonPropertiesString":"","CloudSyncStatus":"Ready","ServerVersionStr":"15.00.4198","ServerVersion":15004198},{"ConnType":"MARIADB","Name":"MariaDB","SettingsSavePath":"/home/josue/.config/navicat/Settings/0/0/MARIADB/MariaDB","ServiceProvider":"Default","Hostname":"localhost","Port":3306,"Username":"josue","Password":"7CC36AE49F23C0D550AEFB436DB4E3E6","SavePassword":true,"ClientDriverVersion":"Default","Encoding":0,"ClientCharacterSet":"","ClientEncoding":65001,"UseKeepAlive":false,"KeepAliveInterval":240,"UseCompression":false,"IsAutoConnect":false,"UseSocketFile":false,"SocketFile":"","SessionLimit":0,"UseCustomDBList":false,"CustomDBList":[],"UseSSL":false,"SSL":{"Mode":"Require","UseAuth":false,"ClientCertFile":"","ClientKeyFile":"","CACert":"","VerifyCA":false,"Cipher":"","RootCert":"","CRLFile":"","WeakCertValidation":true,"AllowInvalidHostName":false,"ClientKeyPassword":"","SaveClientKeyPassword":true},"UseSSH":false,"SSH":{"Host":"","Port":22,"UserName":"","AuthMethod":"Password","Password":"E191AF42327478CC5F143EF279EC4D81","SavePassword":true,"PrivateKeyPath":"","Passphrase":"E191AF42327478CC5F143EF279EC4D81","SavePassphrase":true,"UseCompression":false},"UseHTTP":false,"HTTPTunnel":{"URL":"","EncodeBase64":false,"UsePasswordAuth":false,"Username":"","Password":"E191AF42327478CC5F143EF279EC4D81","SavePassword":true,"UseCertAuth":false,"ClientKey":"","ClientCert":"","CACert":"","Passphrase":"E191AF42327478CC5F143EF279EC4D81","UseProxy":false,"Host":"","Port":8080,"ProxyUsername":"","ProxyPassword":"E191AF42327478CC5F143EF279EC4D81","SaveProxyPassword":true},"Profiles":[],"ActiveServerSettings":"","CreateTime":1684275414,"ModifyTime":1684275414,"NSYCreatedUser":"","NSYModifiedUser":"","NSYModifiedUserUUID":"","NSYCreatedUnixTimestamp":0,"NSYModifiedUnixTimestamp":0,"CommitUUID":"","ConnectionUUID":"","UnknownJsonPropertiesString":"","CloudSyncStatus":"Ready","ServerVersionStr":"10.11.3-MariaDB","ServerVersion":101103}]}]}]}